mathtranslate/__init__.py
mathtranslate/cache.py
mathtranslate/config.py
mathtranslate/encoding.py
mathtranslate/process_file.py
mathtranslate/process_latex.py
mathtranslate/process_text.py
mathtranslate/tencent.py
mathtranslate/translate.py
mathtranslate/translate_arxiv.py
mathtranslate/translate_tex.py
mathtranslate/update.py
mathtranslate/upload_overleaf.py
mathtranslate/utils.py
mathtranslate/tencentcloud/__init__.py
mathtranslate/tencentcloud/common/__init__.py
mathtranslate/tencentcloud/common/abstract_client.py
mathtranslate/tencentcloud/common/abstract_model.py
mathtranslate/tencentcloud/common/common_client.py
mathtranslate/tencentcloud/common/credential.py
mathtranslate/tencentcloud/common/sign.py
mathtranslate/tencentcloud/common/exception/__init__.py
mathtranslate/tencentcloud/common/exception/tencent_cloud_sdk_exception.py
mathtranslate/tencentcloud/common/http/__init__.py
mathtranslate/tencentcloud/common/http/request.py
mathtranslate/tencentcloud/common/profile/__init__.py
mathtranslate/tencentcloud/common/profile/client_profile.py
mathtranslate/tencentcloud/common/profile/http_profile.py
mathtranslate/tencentcloud/tmt/__init__.py
mathtranslate/tencentcloud/tmt/v20180321/__init__.py
mathtranslate/tencentcloud/tmt/v20180321/errorcodes.py
mathtranslate/tencentcloud/tmt/v20180321/models.py
mathtranslate/tencentcloud/tmt/v20180321/tmt_client.py
mathtranslate-3.1.2.dist-info/LICENSE
mathtranslate-3.1.2.dist-info/METADATA
mathtranslate-3.1.2.dist-info/WHEEL
mathtranslate-3.1.2.dist-info/entry_points.txt
mathtranslate-3.1.2.dist-info/top_level.txt
mathtranslate-3.1.2.dist-info/RECORD
