Metadata-Version: 2.1
Name: mathtranslate
Version: 3.1.2
Summary: Translate math-heavy papers
Home-page: https://github.com/SUSYUSTC/MathTranslate
Author: MathTranslate developers
Author-email: susyustc@gmail.com
Classifier: Programming Language :: Python :: 3
Classifier: Operating System :: OS Independent
License-File: LICENSE
Requires-Dist: mtranslate
Requires-Dist: charset-normalizer
Requires-Dist: requests
Requires-Dist: regex
Requires-Dist: tqdm
Requires-Dist: appdata
